git_repo_master/__init__.py
git_repo_master/__main__.py
git_repo_master/app.py
git_repo_master/azure_actions.py
git_repo_master/parser.py
git_repo_master/azure_devops/__init__.py
git_repo_master/azure_devops/branch_locker.py
git_repo_master/azure_devops/pull_request_creator.py
git_repo_master/azure_devops/request.py
git_repo_master-0.1.3.dist-info/LICENSE
git_repo_master-0.1.3.dist-info/METADATA
git_repo_master-0.1.3.dist-info/WHEEL
git_repo_master-0.1.3.dist-info/entry_points.txt
git_repo_master-0.1.3.dist-info/top_level.txt
git_repo_master-0.1.3.dist-info/RECORD
