Metadata-Version: 2.1
Name: git-repo-master
Version: 0.1.3
Summary: Small package to automate actions with git repo on Azure DevOps
Home-page: https://github.com/mustafmst/git-repo-master
Author: Paweł Mstowski
Author-email: pawel.mstowski@gmail.com
License: UNKNOWN
Platform: UNKNOWN
Classifier: Programming Language :: Python :: 3
Classifier: License :: OSI Approved :: MIT License
Classifier: Operating System :: OS Independent
